copy_camera_accuracy/__init__.py
copy_camera_accuracy/copy_camera_accuracy.py
copy_camera_accuracy_2/__init__.py
copy_camera_accuracy_2/copy_camera_accuracy_2.py
copy_camera_selected/__init__.py
copy_camera_selected/copy_camera_selected.py
generate_log_raw_petak/__init__.py
generate_log_raw_petak/generate_log_raw_petak.py
generate_merge_report_camera/__init__.py
generate_merge_report_camera/generate_merge_report_camera.py
generate_report_1/__init__.py
generate_report_1/generate_report_1.py
generate_report_2/__init__.py
generate_report_2/generate_report_2.py
making_directory/__init__.py
making_directory/making_directory.py
process_foto/__init__.py
process_foto/process_foto.py
csv_metashape_generator-0.0.1.dist-info/METADATA
csv_metashape_generator-0.0.1.dist-info/WHEEL
csv_metashape_generator-0.0.1.dist-info/top_level.txt
csv_metashape_generator-0.0.1.dist-info/RECORD
